{
  "version": "0.1.0",
  "friendlyName": "FSR Flex-LT",
  "serviceName": "fsr-flex-lt",
  "manufacturer": "FSR",
  "model": "Flex-LT",
  "buildUrls": {
    "linux": "",
    "mac": "",
    "armv7": "",
    "windows": ""
  },
  "parameters": [
    {
      "parameter": "ipAddress",
      "friendlyName": "IP Address",
      "type": "string",
      "default": "",
      "required": true,
      "placeholder": "Enter the IP address or host name.",
      "tooltip": ""
    }    
  ],
  "commands": [
    {
      "friendlyName": "Connect",
      "editable": false,
      "pattern": "connect",
      "useHex": false,
      "endWith": "n",
      "descriptions": [
        {
          "title": "Description",
          "body": "Connects the tcp socket."
        }
      ]
    },
    {
      "friendlyName": "Close",
      "editable": false,
      "pattern": "close",
      "useHex": false,
      "endWith": "n",
      "descriptions": [
        {
          "title": "Description",
          "body": "Closes the tcp socket."
        }
      ]
    },
    {
      "friendlyName": "Beep",
      "editable": false,
      "pattern": "beep",
      "useHex": false,
      "endWith": "n",
      "descriptions": [
        {
          "title": "Description",
          "body": "Instructs the Flex to Beep."
        }
      ]
    },
    {
      "friendlyName": "Pulse GPIO 1",
      "editable": true,
      "pattern": "pulseIo1",
      "useHex": false,
      "endWith": "n",
      "descriptions": [
        {
          "title": "Description",
          "body": "Instructs the Flex to Pulse GPIO port 1."
        }
      ]
    },
    {
      "friendlyName": "Pulse GPIO 2",
      "editable": true,
      "pattern": "pulseIo2",
      "useHex": false,
      "endWith": "n",
      "descriptions": [
        {
          "title": "Description",
          "body": "Instructs the Flex to Pulse GPIO port 2."
        }
      ]
    },
    {
      "friendlyName": "Pulse GPIO 3",
      "editable": true,
      "pattern": "pulseIo3",
      "useHex": false,
      "endWith": "n",
      "descriptions": [
        {
          "title": "Description",
          "body": "Instructs the Flex to Pulse GPIO port 3."
        }
      ]
    },
    {
      "friendlyName": "Pulse GPIO 4",
      "editable": true,
      "pattern": "pulseIo4",
      "useHex": false,
      "endWith": "n",
      "descriptions": [
        {
          "title": "Description",
          "body": "Instructs the Flex to Pulse GPIO port 4."
        }
      ]
    },
    {
      "friendlyName": "Open GPIO 1",
      "editable": true,
      "pattern": "openIo1",
      "useHex": false,
      "endWith": "n",
      "descriptions": [
        {
          "title": "Description",
          "body": "Instructs the Flex to open GPIO port 1."
        }
      ]
    },
    {
      "friendlyName": "Open GPIO 2",
      "editable": true,
      "pattern": "openIo2",
      "useHex": false,
      "endWith": "n",
      "descriptions": [
        {
          "title": "Description",
          "body": "Instructs the Flex to open GPIO port 2."
        }
      ]
    },
    {
      "friendlyName": "Open GPIO 3",
      "editable": true,
      "pattern": "openIo3",
      "useHex": false,
      "endWith": "n",
      "descriptions": [
        {
          "title": "Description",
          "body": "Instructs the Flex to open GPIO port 3."
        }
      ]
    },
    {
      "friendlyName": "Open GPIO 4",
      "editable": true,
      "pattern": "openIo4",
      "useHex": false,
      "endWith": "n",
      "descriptions": [
        {
          "title": "Description",
          "body": "Instructs the Flex to open GPIO port 4."
        }
      ]
    },
    {
      "friendlyName": "Close GPIO 1",
      "editable": true,
      "pattern": "closeIo1",
      "useHex": false,
      "endWith": "n",
      "descriptions": [
        {
          "title": "Description",
          "body": "Instructs the Flex to close GPIO port 1."
        }
      ]
    },
    {
      "friendlyName": "Close GPIO 2",
      "editable": true,
      "pattern": "closeIo2",
      "useHex": false,
      "endWith": "n",
      "descriptions": [
        {
          "title": "Description",
          "body": "Instructs the Flex to close GPIO port 2."
        }
      ]
    },
    {
      "friendlyName": "Close GPIO 3",
      "editable": true,
      "pattern": "closeIo3",
      "useHex": false,
      "endWith": "n",
      "descriptions": [
        {
          "title": "Description",
          "body": "Instructs the Flex to close GPIO port 3."
        }
      ]
    },
    {
      "friendlyName": "Close GPIO 4",
      "editable": true,
      "pattern": "closeIo4",
      "useHex": false,
      "endWith": "n",
      "descriptions": [
        {
          "title": "Description",
          "body": "Instructs the Flex to close GPIO port 4."
        }
      ]
    },
    {
      "friendlyName": "Sample IR Command",
      "editable": true,
      "pattern": "action = IR 2, 3 \"DVD2\" \"PLAY\"",
      "useHex": false,
      "endWith": "r",
      "descriptions": [
        {
          "title": "Description",
          "body": "Instruct the Flex to send a command from a project library to a project device. action = IR x, y \"Device Name\" \"Command Name\". x is the IR Port Number. y is the number of times to repeat the command. Device name is the EXACT name given to the device in the project. Command Name is the EXACT name given to the desired command in the project."
        }
      ]
    },
    {
      "friendlyName": "Sample Serial Command",
      "editable": true,
      "pattern": "action = SER 4 \"Relay\" \"RELAY CLOSE 1\"",
      "useHex": false,
      "endWith": "r",
      "descriptions": [
        {
          "title": "Description",
          "body": "Instruct the Flex to send a command from a project library to a project device. action = SER x \"Device Name\" \"Command Name\". x is the Serial Port Number. Device name is the EXACT name given to the device in the project. Command Name is the EXACT name given to the desired command in the project."
        }
      ]
    },
    {
      "friendlyName": "Sample Got To Screen Command",
      "editable": true,
      "pattern": "action = GoTo 1",
      "useHex": false,
      "endWith": "r",
      "descriptions": [
        {
          "title": "Description",
          "body": "Instructs the Flex to change to a specified screen called a desktop. Action = GoTo x. x is the number of the desktop to display. You can determine the number for a particular desktop by looking at the Define Screens – Build Screen List tab in the Configuration Utility. Splash is desktop 0 and Home is desktop 1."
        }
      ]
    },
    {
      "friendlyName": "Sample Wait Command",
      "editable": true,
      "pattern": "action = WAIT 100",
      "useHex": false,
      "endWith": "r",
      "descriptions": [
        {
          "title": "Description",
          "body": "Instructs the Flex to pause execution for a specified amount of time. action = WAIT x. x is a value in milliseconds to wait. 100 <= x => 60000. 1 Second = 1000 milliseconds."
        }
      ]
    },
    {
      "friendlyName": "Sample Button Press Command",
      "editable": true,
      "pattern": "action = VPRESS desktop 4 button 3",
      "useHex": false,
      "endWith": "r",
      "descriptions": [
        {
          "title": "Description",
          "body": "Performs a virtual press of the specified button. action = VPRESS Desktop x Button y. x is the number of the desktop containing the button to press. y is the number of the Button or Source to press. The Button / Source number can be determined from the Define Screens – Assign Button Actions tab in the CU. Select the screen containing the button to press and then select the button. Beside the graphic of the button is the designator for that button."
        }
      ]
    },
    {
      "friendlyName": "Sample Source Button Press Command",
      "editable": true,
      "pattern": "action = VPRESS desktop 5 source 6",
      "useHex": false,
      "endWith": "r",
      "descriptions": [
        {
          "title": "Description",
          "body": "Performs a virtual press of the specified button. action = VPRESS Desktop x Button y. x is the number of the desktop containing the button to press. y is the number of the Button or Source to press. The Button / Source number can be determined from the Define Screens – Assign Button Actions tab in the CU. Select the screen containing the button to press and then select the button. Beside the graphic of the button is the designator for that button."
        }
      ]
    },
    {
      "friendlyName": "Sample Button State On Command",
      "editable": true,
      "pattern": "action = SET STATE 1 desktop 3 button 4",
      "useHex": false,
      "endWith": "r",
      "descriptions": [
        {
          "title": "Description",
          "body": "Set the state of a toggle button to a specific value. action = SET STATE x Desktop y Button /Source z. x is the state (0 or 1). y is the Desktop Number. z is the Button/Source Number"
        }
      ]
    },
    {
      "friendlyName": "Sample Inline Serial Message Command",
      "editable": true,
      "pattern": "action = SER 3 INLINE \"ICREC 1 1\"",
      "useHex": false,
      "endWith": "r",
      "descriptions": [
        {
          "title": "Description",
          "body": "Sends a serial command to a device connected to the Flex. action = SER x INLINE “Serial Command”. x is the number of the serial port. Serial Command is the serial command to send to the device. Note: Catch Connect cannot insert hex characters in the Serial Command. "
        }
      ]
    },
    {
      "friendlyName": "Sample Log Command Action Command",
      "editable": true,
      "pattern": "action = LOG \"Source Change\" \"DVD\"",
      "useHex": false,
      "endWith": "r",
      "descriptions": [
        {
          "title": "Description",
          "body": "Register an event in the Flex’s log. action = LOG ‘Event Type’ ‘Event Name’. Event Type is the type of Event that is occurring such as Source Change. Event Name is the specific event that occurs such as DVD."
        }
      ]
    },    
    {
      "friendlyName": "Sample Touch Lockout Command",
      "editable": true,
      "pattern": "action = TOUCH LOCKOUT 100",
      "useHex": false,
      "endWith": "r",
      "descriptions": [
        {
          "title": "Description",
          "body": "Instructs the Flex to ignore all screen touches for a specified amount of time. action = TOUCH LOCKOUT x. x is the amount of time to lock the screen in milliseconds. 100<=x=>360000000. 1 Second = 1000 Milliseconds."
        }
      ]
    }
  ],
  "responses": [
    {
      "friendlyName": "Connection State",
      "editable": false,
      "pattern": "{connected:(.+)$}",
      "useHex": false,
      "useRegularExpression": false,
      "descriptions": [
        {
          "title": "Description",
          "body": "Indicates the TCP connection state."
        }
      ]
    },
    {
      "friendlyName": "Connection Error",
      "editable": false,
      "pattern": "{socketError:(.+)$}",
      "useHex": false,
      "useRegularExpression": false,
      "descriptions": [
        {
          "title": "Description",
          "body": "Indicates a TCP connection error."
        }
      ]
    }    
  ]
}